ram.v
//single port ram module design 

module single_port_ram (
 input [7:0]data,    // 8 bit of input data
 input we,           //Enables write operation
 input [5:0]addr,    //6-bit of adrress to storage the data 
 input clk,  	     //clk pulse
output[7:0]q	     //8-bit of output data 
);

  reg [7:0] ram [63:0]; //actual 64x8 memeory storage 
reg [5:0] addr_reg;   //copy addr to registerd address

always @(posedge clk)
begin 
  if (we)  
    ram[addr]<=data;	// write to RAM using current address
else
  addr_reg<= addr ;	 // write to RAM using previous read address or to store adddr
end
  assign q = ram[addr_reg];   // output 
endmodule


// Dual Port RAM Design.

module dual_port_ram (
  input  [7:0] data_a, data_b,
  input  [5:0] addr_a, addr_b,
  input        we_a, we_b,
  input        clk,
  output wire [7:0] q_a, q_b          
);

  reg [7:0] ram [63:0];           // 64 x 8-bit shared memory
  reg [5:0] addr_a_reg;           // registered address Port a
  reg [5:0] addr_b_reg;           // registered address Port b

  //  Port A 
  always @(posedge clk) begin
    if (we_a && we_b && (addr_a == addr_b))  //checks  values of addr_a& addr_b are same if same collision occurs addr warns where it happens 
      $display("WARNING: Write collision at addr %0d", addr_a);
    else if (we_a)
      ram[addr_a] <= data_a;      // write Port A
    addr_a_reg <= addr_a;         // always latch address
  end

  //  Port B 
  
  always @(posedge clk) begin
    if (!(we_a && we_b && (addr_b == addr_a)))
      if (we_b)
        ram[addr_b] <= data_b;    // write Port B
    addr_b_reg <= addr_b;         // always latch address
  end

  //  outputs 
  
  assign q_a = ram[addr_a_reg];   // output Port A
  assign q_b = ram[addr_b_reg];   // output Port B

endmodule

// loading data into memory from an text(.txt)file 

// module load_memory_file;
 
//   reg [7:0] ram [63:0];   // 64 x 8-bit shared memory
 

//   initial begin
//     $readmemh("memory_data.txt", ram);   // Load hex values from file into ram[]
//     $display("Memory loaded from memory_data.txt");
//     $display("ram[0]=0x%h ram[1]=0x%h ram[2]=0x%h ram[3]=0x%h",
//               ram[0], ram[1], ram[2], ram[3]);
//     $readmemb("memory_data.txt", ram);   // Load binary values from file into ram[]
//     $display("Memory loaded from memory_data.txt");
//     $display("ram[4]=0x%b ram[5]=0x%b ram[6]=0x%h ram[7]=0x%h",
//              ram[4], ram[5], ram[6], ram[7]);
//   end

ram_tb.v
`timescale 1ns / 1ps
`include "ram.v"
module single_port_ram_tb;
  reg [7:0] data;
  reg [5:0] addr;
  reg we;
  reg clk;
  wire [7:0] q;

  single_port_ram dut(.data(data), .addr(addr), .we(we), .clk(clk), .q(q));

  initial begin
    $dumpfile("dump.vcd");
    $dumpvars(0, single_port_ram_tb);
    clk = 1'b1;
    forever #5 clk = ~clk;
  end

  initial begin
    // Write operations is enabled to write data in specific location 
    we   = 1'b1;
    data = 8'h60; addr = 5'd0; #10;
    data = 8'hA1; addr = 5'd1; #10;
    data = 8'h89; addr = 5'd2; #10;
    data = 8'h34; addr = 5'd3; #10;
    data = 8'hC2; addr = 5'd4; #10;
    data = 8'hEF; addr = 5'd5; #10;
    data = 8'hBD; addr = 5'd6; #10;
    data = 8'hFF; addr = 5'd7; #10;

    // Read operations enables when erite operation disabled 
    
    we   = 1'b0;
    addr = 5'd0; #10;
    addr = 5'd1; #10;
    $finish;
  end
endmodule




//Dual Port RAM Design Testbench 


`timescale 1ns / 1ps

module dual_port_ram_tb;

  reg  [7:0] data_a, data_b;
  reg  [5:0] addr_a, addr_b;
  reg        we_a, we_b;
  reg        clk;
  wire [7:0] q_a, q_b;


  
  dual_port_ram dut (
    .data_a (data_a),
    .addr_a (addr_a),
    .we_a   (we_a),
    .data_b (data_b),
    .addr_b (addr_b),
    .we_b   (we_b),
    .clk    (clk),
    .q_a    (q_a),
    .q_b    (q_b)
  );

    initial begin
    $dumpfile("dump.vcd");
    $dumpvars(0, dual_port_ram_tb);
    clk = 1'b0;
    forever #5 clk = ~clk;
  end

 
  initial begin

    we_a   = 1'b0; we_b   = 1'b0;
    data_a = 8'h00; data_b = 8'h00;
    addr_a = 6'd0;  addr_b = 6'd0;
    #10;

    //  Port A Write&Port B Write Simultaneously writes to diffrent addr
    
    we_a = 1'b1; we_b = 1'b1;

    data_a = 8'hA1; addr_a = 6'd0;   
    data_b = 8'hB1; addr_b = 6'd1;   
    #10;

    data_a = 8'hA2; addr_a = 6'd2;   
    data_b = 8'hB2; addr_b = 6'd3;
    #10;

    data_a = 8'hA3; addr_a = 6'd4; 
    data_b = 8'hB3; addr_b = 6'd5; 
   
    #10;

    data_a = 8'hA4; addr_a = 6'd6;  
    data_b = 8'hB4; addr_b = 6'd7;  
    #10;

    
    // the Port a& port b reads simultaneouly from diff addr.
       
    we_a = 1'b0; we_b = 1'b0;

    addr_a = 6'd0; addr_b = 6'd1; #10;  
    addr_a = 6'd2; addr_b = 6'd3; #10;  
    addr_a = 6'd4; addr_b = 6'd5; #10;  
    addr_a = 6'd6; addr_b = 6'd7; #10;  

    
    // Where Port a Writes & port b Reads simultaneoulsy in diff addr
   
    
    we_a = 1'b1; we_b = 1'b0;

    data_a = 8'hFF; addr_a = 6'd8;   
                    addr_b = 6'd0;   
    #10;

    data_a = 8'hEE; addr_a = 6'd9;   
                    addr_b = 6'd2;   
    #10;

    
  
    // Where Port a Reads & Port b Writes simultaneously (different addresses)
    
 
    we_a = 1'b0; we_b = 1'b1;

    data_b = 8'hCC; addr_b = 6'd10;  
                    addr_a = 6'd1;   
    #10;

    data_b = 8'hDD; addr_b = 6'd11;  
    addr_a = 6'd3;   
    #10;

   

    
    //  collision if  (Both ports write to SAME address)
    
    $display(" Collision - Both Ports Write to Same addr  ");
    we_a = 1'b1; we_b = 1'b1; 

    data_a = 8'hAA; addr_a = 6'd20;  
    data_b = 8'hBB; addr_b = 6'd20;  
    #10;
    
    //if collision occurs the Result depends on last Excuted Port either(a,b)

    
  
    $finish;
  end

  initial begin
    $monitor("Time=%0t | we_a=%b we_b=%b | addr_a=%0d addr_b=%0d | data_a=0x%h data_b=0x%h | q_a=0x%h q_b=0x%h",
    $time, we_a, we_b, addr_a, addr_b, data_a, data_b, q_a, q_b);
  end

endmodule

dump.vcd
$date
	Sun Jun 14 07:14:23 2026
$end
$version
	Icarus Verilog
$end
$timescale
	1ps
$end
$scope module dual_port_ram_tb $end
$var wire 8 ! q_b [7:0] $end
$var wire 8 " q_a [7:0] $end
$var reg 6 # addr_a [5:0] $end
$var reg 6 $ addr_b [5:0] $end
$var reg 1 % clk $end
$var reg 8 & data_a [7:0] $end
$var reg 8 ' data_b [7:0] $end
$var reg 1 ( we_a $end
$var reg 1 ) we_b $end
$scope module dut $end
$var wire 6 * addr_a [5:0] $end
$var wire 6 + addr_b [5:0] $end
$var wire 1 % clk $end
$var wire 8 , data_a [7:0] $end
$var wire 8 - data_b [7:0] $end
$var wire 8 . q_a [7:0] $end
$var wire 8 / q_b [7:0] $end
$var wire 1 ( we_a $end
$var wire 1 ) we_b $end
$var reg 6 0 addr_a_reg [5:0] $end
$var reg 6 1 addr_b_reg [5:0] $end
$upscope $end
$upscope $end
$scope module single_port_ram_tb $end
$var wire 8 2 q [7:0] $end
$var reg 6 3 addr [5:0] $end
$var reg 1 4 clk $end
$var reg 8 5 data [7:0] $end
$var reg 1 6 we $end
$scope module dut $end
$var wire 6 7 addr [5:0] $end
$var wire 1 4 clk $end
$var wire 8 8 data [7:0] $end
$var wire 8 9 q [7:0] $end
$var wire 1 6 we $end
$var reg 6 : addr_reg [5:0] $end
$upscope $end
$upscope $end
$enddefinitions $end
$comment Show the parameter values. $end
$dumpall
$end
#0
$dumpvars
bx :
bx 9
b1100000 8
b0 7
16
b1100000 5
14
b0 3
bx 2
bx 1
bx 0
bx /
bx .
b0 -
b0 ,
b0 +
b0 *
0)
0(
b0 '
b0 &
0%
b0 $
b0 #
bx "
bx !
$end
#5000
b0 0
b0 1
04
1%
#10000
14
0%
b1 3
b1 7
b10100001 5
b10100001 8
b1 $
b1 +
b10110001 '
b10110001 -
b10100001 &
b10100001 ,
1)
1(
#15000
b1 1
b10100001 "
b10100001 .
b10110001 !
b10110001 /
04
1%
#20000
14
0%
b10 3
b10 7
b10001001 5
b10001001 8
b11 $
b11 +
b10110010 '
b10110010 -
b10 #
b10 *
b10100010 &
b10100010 ,
#25000
b10100010 "
b10100010 .
b10 0
b10110010 !
b10110010 /
b11 1
04
1%
#30000
14
0%
b11 3
b11 7
b110100 5
b110100 8
b101 $
b101 +
b10110011 '
b10110011 -
b100 #
b100 *
b10100011 &
b10100011 ,
#35000
b10110011 !
b10110011 /
b101 1
b10100011 "
b10100011 .
b100 0
04
1%
#40000
14
0%
b100 3
b100 7
b11000010 5
b11000010 8
b111 $
b111 +
b10110100 '
b10110100 -
b110 #
b110 *
b10100100 &
b10100100 ,
#45000
b10100100 "
b10100100 .
b110 0
b10110100 !
b10110100 /
b111 1
04
1%
#50000
14
0%
b101 3
b101 7
b11101111 5
b11101111 8
b1 $
b1 +
b0 #
b0 *
0)
0(
#55000
b10110001 !
b10110001 /
b1 1
b10100001 "
b10100001 .
b0 0
04
1%
#60000
14
0%
b110 3
b110 7
b10111101 5
b10111101 8
b11 $
b11 +
b10 #
b10 *
#65000
b10100010 "
b10100010 .
b10 0
b10110010 !
b10110010 /
b11 1
04
1%
#70000
14
0%
b111 3
b111 7
b11111111 5
b11111111 8
b101 $
b101 +
b100 #
b100 *
#75000
b10110011 !
b10110011 /
b101 1
b10100011 "
b10100011 .
b100 0
04
1%
#80000
b1100000 2
b1100000 9
b0 :
14
0%
b0 3
b0 7
06
b111 $
b111 +
b110 #
b110 *
#85000
b10100100 "
b10100100 .
b110 0
b10110100 !
b10110100 /
b111 1
04
1%
#90000
b10100001 2
b10100001 9
b1 :
14
0%
b1 3
b1 7
b0 $
b0 +
b1000 #
b1000 *
b11111111 &
b11111111 ,
1(
#95000
b10100001 !
b10100001 /
b0 1
b11111111 "
b11111111 .
b1000 0
04
1%
#100000
14
0%
b10 $
b10 +
b1001 #
b1001 *
b11101110 &
b11101110 ,
